{
    "metadata": {
        "last_updated": "2026-05-26T00:11:02.413688",
        "status": "success"
    },
    "market": {
        "exchange_rate": 1518.777044,
        "stocks": {
            "AAPL": 308.82,
            "TSLA": 426.01,
            "NVDA": 215.33,
            "MSFT": 418.57,
            "GOOGL": 382.97
        },
        "crypto": {
            "BITCOIN": 77166,
            "ETHEREUM": 2109.06,
            "SOLANA": 84.85,
            "RIPPLE": 1.35,
            "CARDANO": 0.243251
        }
    }
}