{
    "metadata": {
        "last_updated": "2026-06-22T23:36:02.319810",
        "status": "success"
    },
    "market": {
        "exchange_rate": 1531.004518,
        "stocks": {
            "AAPL": 297.01,
            "TSLA": 405.05,
            "NVDA": 208.65,
            "005930.KS": 353500.0,
            "MSFT": 367.34,
            "GOOGL": 349.68
        },
        "crypto": {
            "BITCOIN": 63914,
            "ETHEREUM": 1724.11,
            "SOLANA": 71.93,
            "RIPPLE": 1.13,
            "CARDANO": 0.158218
        }
    }
}