{
    "metadata": {
        "last_updated": "2026-04-21T14:50:02.218664",
        "status": "success"
    },
    "market": {
        "exchange_rate": 1470.961883,
        "stocks": {
            "AAPL": 269.34,
            "TSLA": 391.03,
            "NVDA": 201.72,
            "005930.KS": 219000.0,
            "MSFT": 425.01,
            "GOOGL": 337.22
        },
        "crypto": {
            "BITCOIN": 76244,
            "ETHEREUM": 2314.43,
            "SOLANA": 86.35,
            "RIPPLE": 1.44,
            "CARDANO": 0.249642
        }
    }
}