{
    "metadata": {
        "last_updated": "2026-04-30T18:14:43.027723",
        "status": "success"
    },
    "market": {
        "exchange_rate": 1483.344959,
        "stocks": {
            "AAPL": 274.0,
            "TSLA": 380.14,
            "NVDA": 200.7,
            "005930.KS": 220500.0,
            "MSFT": 404.34,
            "GOOGL": 384.98
        },
        "crypto": {
            "BITCOIN": 76231,
            "ETHEREUM": 2255.28,
            "SOLANA": 83.05,
            "RIPPLE": 1.37,
            "CARDANO": 0.245804
        }
    }
}