{
    "metadata": {
        "last_updated": "2026-06-18T09:39:38.719439",
        "status": "success"
    },
    "market": {
        "exchange_rate": 1518.880915,
        "stocks": {
            "AAPL": 295.95,
            "TSLA": 396.38,
            "NVDA": 204.65,
            "005930.KS": 362500.0,
            "MSFT": 378.91,
            "GOOGL": 363.79
        },
        "crypto": {
            "BITCOIN": 64214,
            "ETHEREUM": 1743.83,
            "SOLANA": 71.82,
            "RIPPLE": 1.18,
            "CARDANO": 0.166527
        }
    }
}